{
  "$schema": "rusty.manifold.admission.receipt.v1",
  "operation": "issue_token",
  "request_id": "request.admission.issue",
  "applied": true,
  "prior_authority_revision": 1,
  "resulting_authority_revision": 2,
  "token": {
    "$schema": "rusty.manifold.admission.token.v1",
    "token_id": "token.session.0707070707070707070707070707070707070707070707070707070707070707",
    "identity": {
      "client_id": "client.quest.authorized",
      "platform_subject": "io.github.mesmerprism.rustymanifold.admission.client",
      "signing_fingerprint": "sha256:a1a1a1a1a1a1a1a1a1a1a1a1a1a1a1a1a1a1a1a1a1a1a1a1a1a1a1a1a1a1a1a1"
    },
    "grant_id": "grant.quest.authorized",
    "capabilities": [
      "capability.command.session.list"
    ],
    "issued_at_ms": 2000,
    "expires_at_ms": 22000,
    "issued_authority_revision": 2
  },
  "removed_token_ids": [],
  "rejection_reason": null
}
